foxtail_contact/__init__.py
foxtail_contact/apps.py
foxtail_contact/forms.py
foxtail_contact/settings.py
foxtail_contact/urls.py
foxtail_contact/views.py
foxtail_contact-0.6.0.dist-info/LICENSE
foxtail_contact-0.6.0.dist-info/WHEEL
foxtail_contact-0.6.0.dist-info/METADATA
foxtail_contact-0.6.0.dist-info/RECORD
