Metadata-Version: 2.1
Name: foxtail-contact
Version: 0.6.0
Summary: A simple contact form for Django 
Home-page: https://github.com/dmptrluke/foxtail-contact
Author: Luke Rogers
Author-email: luke@dmptr.com
Requires-Python: >=3.6
Classifier: Programming Language :: Python :: 3
Classifier: Programming Language :: Python :: 3.11
Classifier: Development Status :: 4 - Beta
Classifier: Framework :: Django
Classifier: Intended Audience :: Developers
Classifier: License :: OSI Approved :: MIT License
Classifier: Operating System :: OS Independent
Requires-Dist: django>=4
Requires-Dist: django-mail-templated-simple
Requires-Dist: django-crispy-forms
Requires-Dist: django-recaptcha
Requires-Dist: django-csp-helpers>=0.5.0
